[
  {
    "Result": {
      "Type": { "Name": "Advanced Wafer" },
      "Count": 1
    },
    "Requirements": [
      {
        "Type": { "Name": "Diamond" },
        "Count": 1
      },
      {
        "Type": { "Name": "Raw Silicon" },
        "Count": 2
      },
      {
        "Type": { "Name": "Redstone" },
        "Count": 1
      },
      {
        "Type": { "Name": "Redstone Repeater" },
        "Count": 1
      }
    ]
  },
  {
    "Result": {
      "Type": { "Name": "Aluminum Wire" },
      "Count": 6
    },
    "Requirements": [
      {
        "Type": { "Name": "Aluminum Ingot" },
        "Count": 3
      },
      {
        "Type": { "Name": "Wool" },
        "Count": 6
      }
    ]
  },
  {
    "Result": {
      "Type": { "Name": "Basic Wafer" },
      "Count": 3
    },
    "Requirements": [
      {
        "Type": { "Name": "Diamond" },
        "Count": 1
      },
      {
        "Type": { "Name": "Raw Silicon" },
        "Count": 2
      },
      {
        "Type": { "Name": "Redstone" },
        "Count": 1
      },
      {
        "Type": { "Name": "Redstone Torch" },
        "Count": 1
      }
    ]
  },  
  {
    "Result": {
      "Type": { "Name": "Heavy Oxygen Tank" },
      "Count": 1
    },
    "Requirements": [
      {
        "Type": { "Name": "Compressed Steel" },
        "Count": 3
      },
      {
        "Type": { "Name": "Red Wool" },
        "Count": 3
      },
      {
        "Type": { "Name": "Tin Canister" },
        "Count": 3
      }
    ]
  },
  {
    "Result": {
      "Type": { "Name": "Light Oxygen Tank" },
      "Count": 1
    },
    "Requirements": [
      {
        "Type": { "Name": "Compressed Copper" },
        "Count": 1
      },
      {
        "Type": { "Name": "Lime Wool" },
        "Count": 1
      },
      {
        "Type": { "Name": "Tin Canister" },
        "Count": 1
      }
    ]
  },
  {
    "Result": {
      "Type": { "Name": "Medium Oxygen Tank" },
      "Count": 1
    },
    "Requirements": [
      {
        "Type": { "Name": "Compressed Tin" },
        "Count": 2
      },
      {
        "Type": { "Name": "Orange Wool" },
        "Count": 2
      },
      {
        "Type": { "Name": "Tin Canister" },
        "Count": 2
      }
    ]
  }, 
  {
    "Result": {
      "Type": { "Name": "Nose Cone" },
      "Count": 1
    },
    "Requirements": [
      {
        "Type": { "Name": "Heavy Duty Plating" },
        "Count": 3
      },
      {
        "Type": { "Name": "Redstone Torch" },
        "Count": 1
      }
    ]
  },
  {
    "Result": {
      "Type": { "Name": "Oxygen Concentrator" },
      "Count": 3
    },
    "Requirements": [
      {
        "Type": { "Name": "Air Vent" },
        "Count": 1
      },
      {
        "Type": { "Name": "Compressed Steel" },
        "Count": 4
      },
      {
        "Type": { "Name": "Compressed Tin" },
        "Count": 3
      },
      {
        "Type": { "Name": "Tin Canister" },
        "Count": 1
      }
    ]
  },
  {
    "Result": {
      "Type": { "Name": "Oxygen Gear" },
      "Count": 3
    },
    "Requirements": [
      {
        "Type": { "Name": "Oxygen Concentrator" },
        "Count": 1
      },
      {
        "Type": { "Name": "Oxygen Pipe" },
        "Count": 5
      }
    ]
  },
  {
    "Result": {
      "Type": { "Name": "Oxygen Mask" },
      "Count": 3
    },
    "Requirements": [
      {
        "Type": { "Name": "Iron Helmet" },
        "Count": 1
      },
      {
        "Type": { "Name": "Glass Pane" },
        "Count": 8
      }
    ]
  },  
  {
    "Result": {
      "Type": { "Name": "Oxygen Pipe" },
      "Count": 6
    },
    "Requirements": [
      {
        "Type": { "Name": "Glass Pane" },
        "Count": 6
      }
    ]
  },
  {
    "Result": {
      "Type": { "Name": "Rocket Engine" },
      "Count": 1
    },
    "Requirements": [
      {
        "Type": { "Name": "Air Vent" },
        "Count": 1
      },
      {
        "Type": { "Name": "Flint and Steel" },
        "Count": 1
      },      
      {
        "Type": { "Name": "Heavy Duty Plating" },
        "Count": 4
      },
      {
        "Type": { "Name": "Stone Button" },
        "Count": 1
      },
      {
        "Type": { "Name": "Tin Canister" },
        "Count": 1
      }
    ]
  },
  {
    "Result": {
      "Type": { "Name": "Rocket Fin" },
      "Count": 1
    },
    "Requirements": [
      {
        "Type": { "Name": "Compressed Steel" },
        "Count": 2
      },
      {
        "Type": { "Name": "Heavy Duty Plating" },
        "Count": 4
      }
    ]
  },
  {
    "Result": {
      "Type": { "Name": "Tier 1 Rocket" },
      "Count": 1
    },
    "Requirements": [
      {
        "Type": { "Name": "Heavy Duty Plating" },
        "Count": 8
      },
      {
        "Type": { "Name": "Nose Cone" },
        "Count": 1
      },
      {
        "Type": { "Name": "Rocket Engine" },
        "Count": 1
      },
      {
        "Type": { "Name": "Rocket Fin" },
        "Count": 4
      }
    ]
  }
]